{"cameraMode":{"drawMode":0,"name":"Shaded","section":"Shading Mode"},"sceneLighting":true,"audioPlay":false,"sceneViewState":{"showFog":true,"showMaterialUpdate":false,"showSkybox":true,"showFlares":true,"showImageEffects":true,"showParticleSystems":true},"in2DMode":false,"pivot":{"x":19.977928161621095,"y":0.1652652472257614,"z":27.872310638427736},"rotation":{"x":0.03363112732768059,"y":0.36081385612487795,"z":-0.013762025162577629,"w":0.9330006241798401},"size":30.247783660888673,"orthographic":false}